{
	"configurations" : 
	[
		{
			"directories" : 
			[
				{
					"build" : ".",
					"childIndexes" : 
					[
						1,
						4,
						15
					],
					"hasInstallRule" : true,
					"jsonFile" : "directory-.-Debug-f5ebdc15457944623624.json",
					"minimumCMakeVersion" : 
					{
						"string" : "3.26"
					},
					"projectIndex" : 0,
					"source" : ".",
					"targetIndexes" : 
					[
						147
					]
				},
				{
					"build" : "rapidcheck",
					"childIndexes" : 
					[
						2,
						3
					],
					"hasInstallRule" : true,
					"jsonFile" : "directory-rapidcheck-Debug-8d124f8036c3184c5079.json",
					"minimumCMakeVersion" : 
					{
						"string" : "3.16"
					},
					"parentIndex" : 0,
					"projectIndex" : 1,
					"source" : "rapidcheck",
					"targetIndexes" : 
					[
						148
					]
				},
				{
					"build" : "rapidcheck/ext",
					"jsonFile" : "directory-rapidcheck.ext-Debug-efb138ecdaeaac2a9c8a.json",
					"minimumCMakeVersion" : 
					{
						"string" : "3.16"
					},
					"parentIndex" : 1,
					"projectIndex" : 1,
					"source" : "rapidcheck/ext"
				},
				{
					"build" : "rapidcheck/extras",
					"jsonFile" : "directory-rapidcheck.extras-Debug-64937093605dea004f73.json",
					"minimumCMakeVersion" : 
					{
						"string" : "3.16"
					},
					"parentIndex" : 1,
					"projectIndex" : 1,
					"source" : "rapidcheck/extras"
				},
				{
					"build" : "_deps/sdsl-build",
					"childIndexes" : 
					[
						5,
						11,
						13,
						14
					],
					"hasInstallRule" : true,
					"jsonFile" : "directory-_deps.sdsl-build-Debug-19d490596f1e79895da0.json",
					"minimumCMakeVersion" : 
					{
						"string" : "2.8.11"
					},
					"parentIndex" : 0,
					"projectIndex" : 2,
					"source" : "cmake-build-debug/_deps/sdsl-src",
					"targetIndexes" : 
					[
						215
					]
				},
				{
					"build" : "_deps/sdsl-build/external",
					"childIndexes" : 
					[
						6,
						10
					],
					"hasInstallRule" : true,
					"jsonFile" : "directory-_deps.sdsl-build.external-Debug-02403ee2c1af5789a57e.json",
					"minimumCMakeVersion" : 
					{
						"string" : "2.8.11"
					},
					"parentIndex" : 4,
					"projectIndex" : 2,
					"source" : "cmake-build-debug/_deps/sdsl-src/external"
				},
				{
					"build" : "_deps/sdsl-build/external/libdivsufsort",
					"childIndexes" : 
					[
						7,
						8,
						9
					],
					"hasInstallRule" : true,
					"jsonFile" : "directory-_deps.sdsl-build.external.libdivsufsort-Debug-070331e11a332c8f7af5.json",
					"minimumCMakeVersion" : 
					{
						"string" : "2.4.4"
					},
					"parentIndex" : 5,
					"projectIndex" : 3,
					"source" : "cmake-build-debug/_deps/sdsl-src/external/libdivsufsort",
					"targetIndexes" : 
					[
						214
					]
				},
				{
					"build" : "_deps/sdsl-build/external/libdivsufsort/pkgconfig",
					"hasInstallRule" : true,
					"jsonFile" : "directory-_deps.sdsl-build.external.libdivsufsort.pkgconfig-Debug-ccf305c66193cb670a10.json",
					"minimumCMakeVersion" : 
					{
						"string" : "2.4.4"
					},
					"parentIndex" : 6,
					"projectIndex" : 3,
					"source" : "cmake-build-debug/_deps/sdsl-src/external/libdivsufsort/pkgconfig"
				},
				{
					"build" : "_deps/sdsl-build/external/libdivsufsort/include",
					"hasInstallRule" : true,
					"jsonFile" : "directory-_deps.sdsl-build.external.libdivsufsort.include-Debug-eee7a3bd1daf6fa2ad87.json",
					"minimumCMakeVersion" : 
					{
						"string" : "2.4.4"
					},
					"parentIndex" : 6,
					"projectIndex" : 3,
					"source" : "cmake-build-debug/_deps/sdsl-src/external/libdivsufsort/include"
				},
				{
					"build" : "_deps/sdsl-build/external/libdivsufsort/lib",
					"hasInstallRule" : true,
					"jsonFile" : "directory-_deps.sdsl-build.external.libdivsufsort.lib-Debug-ed36d8522157819b5dad.json",
					"minimumCMakeVersion" : 
					{
						"string" : "2.4.4"
					},
					"parentIndex" : 6,
					"projectIndex" : 3,
					"source" : "cmake-build-debug/_deps/sdsl-src/external/libdivsufsort/lib",
					"targetIndexes" : 
					[
						75,
						77
					]
				},
				{
					"build" : "_deps/sdsl-build/external/googletest/googletest",
					"hasInstallRule" : true,
					"jsonFile" : "directory-_deps.sdsl-build.external.googletest.googletest-Debug-31df6cf922eb1b7a7418.json",
					"minimumCMakeVersion" : 
					{
						"string" : "2.6.4"
					},
					"parentIndex" : 5,
					"projectIndex" : 4,
					"source" : "cmake-build-debug/_deps/sdsl-src/external/googletest/googletest",
					"targetIndexes" : 
					[
						79,
						80
					]
				},
				{
					"build" : "_deps/sdsl-build/include",
					"childIndexes" : 
					[
						12
					],
					"hasInstallRule" : true,
					"jsonFile" : "directory-_deps.sdsl-build.include-Debug-c6626027372b3b5064e0.json",
					"minimumCMakeVersion" : 
					{
						"string" : "2.8.11"
					},
					"parentIndex" : 4,
					"projectIndex" : 2,
					"source" : "cmake-build-debug/_deps/sdsl-src/include"
				},
				{
					"build" : "_deps/sdsl-build/include/sdsl",
					"hasInstallRule" : true,
					"jsonFile" : "directory-_deps.sdsl-build.include.sdsl-Debug-d0f81083d0a180b7138c.json",
					"minimumCMakeVersion" : 
					{
						"string" : "2.8.11"
					},
					"parentIndex" : 11,
					"projectIndex" : 2,
					"source" : "cmake-build-debug/_deps/sdsl-src/include/sdsl"
				},
				{
					"build" : "_deps/sdsl-build/lib",
					"hasInstallRule" : true,
					"jsonFile" : "directory-_deps.sdsl-build.lib-Debug-fcbde8b1025bb7339332.json",
					"minimumCMakeVersion" : 
					{
						"string" : "2.8.11"
					},
					"parentIndex" : 4,
					"projectIndex" : 2,
					"source" : "cmake-build-debug/_deps/sdsl-src/lib",
					"targetIndexes" : 
					[
						167
					]
				},
				{
					"build" : "_deps/sdsl-build/test",
					"jsonFile" : "directory-_deps.sdsl-build.test-Debug-1b89c148c4d885552a69.json",
					"minimumCMakeVersion" : 
					{
						"string" : "2.8.11"
					},
					"parentIndex" : 4,
					"projectIndex" : 2,
					"source" : "cmake-build-debug/_deps/sdsl-src/test",
					"targetIndexes" : 
					[
						0,
						1,
						2,
						3,
						4,
						5,
						6,
						7,
						8,
						9,
						10,
						11,
						12,
						13,
						14,
						15,
						16,
						17,
						18,
						19,
						20,
						21,
						22,
						23,
						24,
						25,
						26,
						27,
						28,
						29,
						30,
						31,
						32,
						33,
						34,
						35,
						36,
						37,
						38,
						39,
						40,
						41,
						42,
						43,
						44,
						45,
						46,
						47,
						48,
						49,
						50,
						51,
						52,
						53,
						54,
						55,
						56,
						57,
						58,
						59,
						60,
						61,
						62,
						63,
						64,
						65,
						66,
						67,
						68,
						69,
						70,
						71,
						72,
						73,
						78,
						81,
						82,
						83,
						84,
						85,
						86,
						87,
						88,
						89,
						90,
						91,
						92,
						93,
						94,
						95,
						96,
						97,
						98,
						99,
						100,
						101,
						102,
						103,
						104,
						105,
						106,
						107,
						108,
						109,
						110,
						111,
						112,
						113,
						114,
						115,
						116,
						117,
						118,
						119,
						120,
						121,
						122,
						123,
						124,
						125,
						126,
						127,
						128,
						129,
						130,
						131,
						132,
						133,
						134,
						135,
						136,
						137,
						138,
						139,
						140,
						141,
						142,
						143,
						144,
						145,
						146,
						149,
						150,
						151,
						152,
						153,
						154,
						155,
						156,
						157,
						158,
						159,
						160,
						161,
						162,
						163,
						164,
						165,
						166,
						168,
						169,
						170,
						171,
						172,
						173,
						174,
						175,
						176,
						177,
						178,
						179,
						180,
						181,
						182,
						183,
						184,
						185,
						186,
						187,
						188,
						189,
						190,
						191,
						192,
						193,
						194,
						195,
						196,
						197,
						198,
						199,
						200,
						201,
						202,
						203,
						204,
						205,
						206,
						207,
						208,
						209,
						210,
						211,
						212,
						216,
						217,
						218,
						219,
						220,
						221,
						222,
						223,
						224,
						225,
						226,
						227,
						228,
						229,
						230
					]
				},
				{
					"build" : "_deps/divsufsort-build",
					"childIndexes" : 
					[
						16,
						17,
						18
					],
					"hasInstallRule" : true,
					"jsonFile" : "directory-_deps.divsufsort-build-Debug-0be0d90d53f26b7bc0b4.json",
					"minimumCMakeVersion" : 
					{
						"string" : "2.4"
					},
					"parentIndex" : 0,
					"projectIndex" : 5,
					"source" : "cmake-build-debug/_deps/divsufsort-src",
					"targetIndexes" : 
					[
						213
					]
				},
				{
					"build" : "_deps/divsufsort-build/pkgconfig",
					"hasInstallRule" : true,
					"jsonFile" : "directory-_deps.divsufsort-build.pkgconfig-Debug-be96900e349f29f3f543.json",
					"minimumCMakeVersion" : 
					{
						"string" : "2.4"
					},
					"parentIndex" : 15,
					"projectIndex" : 5,
					"source" : "cmake-build-debug/_deps/divsufsort-src/pkgconfig"
				},
				{
					"build" : "_deps/divsufsort-build/include",
					"hasInstallRule" : true,
					"jsonFile" : "directory-_deps.divsufsort-build.include-Debug-c63eaf4e0d4da8ba02cb.json",
					"minimumCMakeVersion" : 
					{
						"string" : "2.4"
					},
					"parentIndex" : 15,
					"projectIndex" : 5,
					"source" : "cmake-build-debug/_deps/divsufsort-src/include"
				},
				{
					"build" : "_deps/divsufsort-build/lib",
					"hasInstallRule" : true,
					"jsonFile" : "directory-_deps.divsufsort-build.lib-Debug-167d21b960a0bf24a784.json",
					"minimumCMakeVersion" : 
					{
						"string" : "2.4"
					},
					"parentIndex" : 15,
					"projectIndex" : 5,
					"source" : "cmake-build-debug/_deps/divsufsort-src/lib",
					"targetIndexes" : 
					[
						74,
						76
					]
				}
			],
			"name" : "Debug",
			"projects" : 
			[
				{
					"childIndexes" : 
					[
						1,
						2,
						5
					],
					"directoryIndexes" : 
					[
						0
					],
					"name" : "rapid_check",
					"targetIndexes" : 
					[
						147
					]
				},
				{
					"directoryIndexes" : 
					[
						1,
						2,
						3
					],
					"name" : "rapidcheck",
					"parentIndex" : 0,
					"targetIndexes" : 
					[
						148
					]
				},
				{
					"childIndexes" : 
					[
						3,
						4
					],
					"directoryIndexes" : 
					[
						4,
						5,
						11,
						12,
						13,
						14
					],
					"name" : "sdsl",
					"parentIndex" : 0,
					"targetIndexes" : 
					[
						0,
						1,
						2,
						3,
						4,
						5,
						6,
						7,
						8,
						9,
						10,
						11,
						12,
						13,
						14,
						15,
						16,
						17,
						18,
						19,
						20,
						21,
						22,
						23,
						24,
						25,
						26,
						27,
						28,
						29,
						30,
						31,
						32,
						33,
						34,
						35,
						36,
						37,
						38,
						39,
						40,
						41,
						42,
						43,
						44,
						45,
						46,
						47,
						48,
						49,
						50,
						51,
						52,
						53,
						54,
						55,
						56,
						57,
						58,
						59,
						60,
						61,
						62,
						63,
						64,
						65,
						66,
						67,
						68,
						69,
						70,
						71,
						72,
						73,
						78,
						81,
						82,
						83,
						84,
						85,
						86,
						87,
						88,
						89,
						90,
						91,
						92,
						93,
						94,
						95,
						96,
						97,
						98,
						99,
						100,
						101,
						102,
						103,
						104,
						105,
						106,
						107,
						108,
						109,
						110,
						111,
						112,
						113,
						114,
						115,
						116,
						117,
						118,
						119,
						120,
						121,
						122,
						123,
						124,
						125,
						126,
						127,
						128,
						129,
						130,
						131,
						132,
						133,
						134,
						135,
						136,
						137,
						138,
						139,
						140,
						141,
						142,
						143,
						144,
						145,
						146,
						149,
						150,
						151,
						152,
						153,
						154,
						155,
						156,
						157,
						158,
						159,
						160,
						161,
						162,
						163,
						164,
						165,
						166,
						167,
						168,
						169,
						170,
						171,
						172,
						173,
						174,
						175,
						176,
						177,
						178,
						179,
						180,
						181,
						182,
						183,
						184,
						185,
						186,
						187,
						188,
						189,
						190,
						191,
						192,
						193,
						194,
						195,
						196,
						197,
						198,
						199,
						200,
						201,
						202,
						203,
						204,
						205,
						206,
						207,
						208,
						209,
						210,
						211,
						212,
						215,
						216,
						217,
						218,
						219,
						220,
						221,
						222,
						223,
						224,
						225,
						226,
						227,
						228,
						229,
						230
					]
				},
				{
					"directoryIndexes" : 
					[
						6,
						7,
						8,
						9
					],
					"name" : "libdivsufsort",
					"parentIndex" : 2,
					"targetIndexes" : 
					[
						75,
						77,
						214
					]
				},
				{
					"directoryIndexes" : 
					[
						10
					],
					"name" : "gtest",
					"parentIndex" : 2,
					"targetIndexes" : 
					[
						79,
						80
					]
				},
				{
					"directoryIndexes" : 
					[
						15,
						16,
						17,
						18
					],
					"name" : "libdivsufsort",
					"parentIndex" : 0,
					"targetIndexes" : 
					[
						74,
						76,
						213
					]
				}
			],
			"targets" : 
			[
				{
					"directoryIndex" : 14,
					"id" : "bit-vector-test::@c593a3635781ae508a1e",
					"jsonFile" : "target-bit-vector-test-Debug-e2c33fdcde24016faee3.json",
					"name" : "bit-vector-test",
					"projectIndex" : 2
				},
				{
					"directoryIndex" : 14,
					"id" : "bit-vector-test_bit-vec.CRAFTED-32::@c593a3635781ae508a1e",
					"jsonFile" : "target-bit-vector-test_bit-vec.CRAFTED-32-Debug-eed75dc26a933e302861.json",
					"name" : "bit-vector-test_bit-vec.CRAFTED-32",
					"projectIndex" : 2
				},
				{
					"directoryIndex" : 14,
					"id" : "bit-vector-test_bit-vec.CRAFTED-BLOCK-0::@c593a3635781ae508a1e",
					"jsonFile" : "target-bit-vector-test_bit-vec.CRAFTED-BLOCK-0-Debug-95f0921b1b087c344b3c.json",
					"name" : "bit-vector-test_bit-vec.CRAFTED-BLOCK-0",
					"projectIndex" : 2
				},
				{
					"directoryIndex" : 14,
					"id" : "bit-vector-test_bit-vec.CRAFTED-BLOCK-1::@c593a3635781ae508a1e",
					"jsonFile" : "target-bit-vector-test_bit-vec.CRAFTED-BLOCK-1-Debug-126773e01d5c5be74ff5.json",
					"name" : "bit-vector-test_bit-vec.CRAFTED-BLOCK-1",
					"projectIndex" : 2
				},
				{
					"directoryIndex" : 14,
					"id" : "bit-vector-test_bit-vec.CRAFTED-MAT-SELECT::@c593a3635781ae508a1e",
					"jsonFile" : "target-bit-vector-test_bit-vec.CRAFTED-MAT-SELECT-Debug-7ea446d405584e3816b0.json",
					"name" : "bit-vector-test_bit-vec.CRAFTED-MAT-SELECT",
					"projectIndex" : 2
				},
				{
					"directoryIndex" : 14,
					"id" : "bit-vector-test_bit-vec.CRAFTED-SPARSE-0::@c593a3635781ae508a1e",
					"jsonFile" : "target-bit-vector-test_bit-vec.CRAFTED-SPARSE-0-Debug-12d55e5ae0b40811cfa3.json",
					"name" : "bit-vector-test_bit-vec.CRAFTED-SPARSE-0",
					"projectIndex" : 2
				},
				{
					"directoryIndex" : 14,
					"id" : "bit-vector-test_bit-vec.CRAFTED-SPARSE-1::@c593a3635781ae508a1e",
					"jsonFile" : "target-bit-vector-test_bit-vec.CRAFTED-SPARSE-1-Debug-e1e15f92826dbfd11c7c.json",
					"name" : "bit-vector-test_bit-vec.CRAFTED-SPARSE-1",
					"projectIndex" : 2
				},
				{
					"directoryIndex" : 14,
					"id" : "bit-vector-test_int-vec.0.1.0::@c593a3635781ae508a1e",
					"jsonFile" : "target-bit-vector-test_int-vec.0.1.0-Debug-d773b575359c7c469a0f.json",
					"name" : "bit-vector-test_int-vec.0.1.0",
					"projectIndex" : 2
				},
				{
					"directoryIndex" : 14,
					"id" : "bit-vector-test_int-vec.1.1.0::@c593a3635781ae508a1e",
					"jsonFile" : "target-bit-vector-test_int-vec.1.1.0-Debug-10e1abf4ecd5714b2f1d.json",
					"name" : "bit-vector-test_int-vec.1.1.0",
					"projectIndex" : 2
				},
				{
					"directoryIndex" : 14,
					"id" : "bit-vector-test_int-vec.10.1.0::@c593a3635781ae508a1e",
					"jsonFile" : "target-bit-vector-test_int-vec.10.1.0-Debug-845d7e41a9b0714ad643.json",
					"name" : "bit-vector-test_int-vec.10.1.0",
					"projectIndex" : 2
				},
				{
					"directoryIndex" : 14,
					"id" : "bit-vector-test_int-vec.1000000.1.0::@c593a3635781ae508a1e",
					"jsonFile" : "target-bit-vector-test_int-vec.1000000.1.0-Debug-3793fcd562260564f912.json",
					"name" : "bit-vector-test_int-vec.1000000.1.0",
					"projectIndex" : 2
				},
				{
					"directoryIndex" : 14,
					"id" : "bit-vector-test_int-vec.1000000.1.1::@c593a3635781ae508a1e",
					"jsonFile" : "target-bit-vector-test_int-vec.1000000.1.1-Debug-4a01f27d613e94d3eae5.json",
					"name" : "bit-vector-test_int-vec.1000000.1.1",
					"projectIndex" : 2
				},
				{
					"directoryIndex" : 14,
					"id" : "bit-vector-test_int-vec.1000000.1.r.815::@c593a3635781ae508a1e",
					"jsonFile" : "target-bit-vector-test_int-vec.1000000.1.r.815-Debug-8ce29bba22d535cdb095.json",
					"name" : "bit-vector-test_int-vec.1000000.1.r.815",
					"projectIndex" : 2
				},
				{
					"directoryIndex" : 14,
					"id" : "bit-vector-test_int-vec.1024.1.r.898::@c593a3635781ae508a1e",
					"jsonFile" : "target-bit-vector-test_int-vec.1024.1.r.898-Debug-fb1eeb4937a24eeffdf5.json",
					"name" : "bit-vector-test_int-vec.1024.1.r.898",
					"projectIndex" : 2
				},
				{
					"directoryIndex" : 14,
					"id" : "bit-vector-test_int-vec.11.1.1::@c593a3635781ae508a1e",
					"jsonFile" : "target-bit-vector-test_int-vec.11.1.1-Debug-0c4f62036dab8b102fdb.json",
					"name" : "bit-vector-test_int-vec.11.1.1",
					"projectIndex" : 2
				},
				{
					"directoryIndex" : 14,
					"id" : "bit-vector-test_int-vec.12.1.0::@c593a3635781ae508a1e",
					"jsonFile" : "target-bit-vector-test_int-vec.12.1.0-Debug-dc399f3c93257026382a.json",
					"name" : "bit-vector-test_int-vec.12.1.0",
					"projectIndex" : 2
				},
				{
					"directoryIndex" : 14,
					"id" : "bit-vector-test_int-vec.128.1.r.73::@c593a3635781ae508a1e",
					"jsonFile" : "target-bit-vector-test_int-vec.128.1.r.73-Debug-8ac4a44f198cdbf5edd3.json",
					"name" : "bit-vector-test_int-vec.128.1.r.73",
					"projectIndex" : 2
				},
				{
					"directoryIndex" : 14,
					"id" : "bit-vector-test_int-vec.13.1.1::@c593a3635781ae508a1e",
					"jsonFile" : "target-bit-vector-test_int-vec.13.1.1-Debug-143f0638395c00839709.json",
					"name" : "bit-vector-test_int-vec.13.1.1",
					"projectIndex" : 2
				},
				{
					"directoryIndex" : 14,
					"id" : "bit-vector-test_int-vec.14.1.0::@c593a3635781ae508a1e",
					"jsonFile" : "target-bit-vector-test_int-vec.14.1.0-Debug-8bed7022d29f2fd9a1bb.json",
					"name" : "bit-vector-test_int-vec.14.1.0",
					"projectIndex" : 2
				},
				{
					"directoryIndex" : 14,
					"id" : "bit-vector-test_int-vec.15.1.1::@c593a3635781ae508a1e",
					"jsonFile" : "target-bit-vector-test_int-vec.15.1.1-Debug-600413a96ffcd8f0b9c3.json",
					"name" : "bit-vector-test_int-vec.15.1.1",
					"projectIndex" : 2
				},
				{
					"directoryIndex" : 14,
					"id" : "bit-vector-test_int-vec.16.1.r.42::@c593a3635781ae508a1e",
					"jsonFile" : "target-bit-vector-test_int-vec.16.1.r.42-Debug-45b5747a19388c6d5cc5.json",
					"name" : "bit-vector-test_int-vec.16.1.r.42",
					"projectIndex" : 2
				},
				{
					"directoryIndex" : 14,
					"id" : "bit-vector-test_int-vec.2048.1.r.5432::@c593a3635781ae508a1e",
					"jsonFile" : "target-bit-vector-test_int-vec.2048.1.r.5432-Debug-e7e52d5c99a654df388c.json",
					"name" : "bit-vector-test_int-vec.2048.1.r.5432",
					"projectIndex" : 2
				},
				{
					"directoryIndex" : 14,
					"id" : "bit-vector-test_int-vec.256.1.r.4887::@c593a3635781ae508a1e",
					"jsonFile" : "target-bit-vector-test_int-vec.256.1.r.4887-Debug-b7e0147ad75a3b4c0935.json",
					"name" : "bit-vector-test_int-vec.256.1.r.4887",
					"projectIndex" : 2
				},
				{
					"directoryIndex" : 14,
					"id" : "bit-vector-test_int-vec.32.1.r.111::@c593a3635781ae508a1e",
					"jsonFile" : "target-bit-vector-test_int-vec.32.1.r.111-Debug-b4e8cffa67fe7dfdec9d.json",
					"name" : "bit-vector-test_int-vec.32.1.r.111",
					"projectIndex" : 2
				},
				{
					"directoryIndex" : 14,
					"id" : "bit-vector-test_int-vec.4096.1.r.793::@c593a3635781ae508a1e",
					"jsonFile" : "target-bit-vector-test_int-vec.4096.1.r.793-Debug-ff7cd77f9f1cf599d8c8.json",
					"name" : "bit-vector-test_int-vec.4096.1.r.793",
					"projectIndex" : 2
				},
				{
					"directoryIndex" : 14,
					"id" : "bit-vector-test_int-vec.512.1.r.432::@c593a3635781ae508a1e",
					"jsonFile" : "target-bit-vector-test_int-vec.512.1.r.432-Debug-97f964d3d69c3ffa6fbe.json",
					"name" : "bit-vector-test_int-vec.512.1.r.432",
					"projectIndex" : 2
				},
				{
					"directoryIndex" : 14,
					"id" : "bit-vector-test_int-vec.64.1.r.222::@c593a3635781ae508a1e",
					"jsonFile" : "target-bit-vector-test_int-vec.64.1.r.222-Debug-bbfea32c9c1d969b8940.json",
					"name" : "bit-vector-test_int-vec.64.1.r.222",
					"projectIndex" : 2
				},
				{
					"directoryIndex" : 14,
					"id" : "bit-vector-test_int-vec.7.1.1::@c593a3635781ae508a1e",
					"jsonFile" : "target-bit-vector-test_int-vec.7.1.1-Debug-df1d2749ea143c447bea.json",
					"name" : "bit-vector-test_int-vec.7.1.1",
					"projectIndex" : 2
				},
				{
					"directoryIndex" : 14,
					"id" : "bit-vector-test_int-vec.8.1.0::@c593a3635781ae508a1e",
					"jsonFile" : "target-bit-vector-test_int-vec.8.1.0-Debug-61cc129d842182760a0b.json",
					"name" : "bit-vector-test_int-vec.8.1.0",
					"projectIndex" : 2
				},
				{
					"directoryIndex" : 14,
					"id" : "bit-vector-test_int-vec.8.1.r.17::@c593a3635781ae508a1e",
					"jsonFile" : "target-bit-vector-test_int-vec.8.1.r.17-Debug-54e6fd1a4cebb4e87b59.json",
					"name" : "bit-vector-test_int-vec.8.1.r.17",
					"projectIndex" : 2
				},
				{
					"directoryIndex" : 14,
					"id" : "bit-vector-test_int-vec.8192.1.r.1043::@c593a3635781ae508a1e",
					"jsonFile" : "target-bit-vector-test_int-vec.8192.1.r.1043-Debug-6d717d52f3207d47431e.json",
					"name" : "bit-vector-test_int-vec.8192.1.r.1043",
					"projectIndex" : 2
				},
				{
					"directoryIndex" : 14,
					"id" : "bit-vector-test_int-vec.9.1.1::@c593a3635781ae508a1e",
					"jsonFile" : "target-bit-vector-test_int-vec.9.1.1-Debug-e4a81a5dbffbdbf3d2dc.json",
					"name" : "bit-vector-test_int-vec.9.1.1",
					"projectIndex" : 2
				},
				{
					"directoryIndex" : 14,
					"id" : "bit_vector_generator::@c593a3635781ae508a1e",
					"jsonFile" : "target-bit_vector_generator-Debug-9c3784301d0207745a7d.json",
					"name" : "bit_vector_generator",
					"projectIndex" : 2
				},
				{
					"directoryIndex" : 14,
					"id" : "bit_vector_test::@c593a3635781ae508a1e",
					"jsonFile" : "target-bit_vector_test-Debug-37c0dda028cf9bdb2a63.json",
					"name" : "bit_vector_test",
					"projectIndex" : 2
				},
				{
					"directoryIndex" : 14,
					"id" : "bits-test::@c593a3635781ae508a1e",
					"jsonFile" : "target-bits-test-Debug-54b20ee8ca0398f14d0a.json",
					"name" : "bits-test",
					"projectIndex" : 2
				},
				{
					"directoryIndex" : 14,
					"id" : "bits_test::@c593a3635781ae508a1e",
					"jsonFile" : "target-bits_test-Debug-2c0982684394cd22f456.json",
					"name" : "bits_test",
					"projectIndex" : 2
				},
				{
					"directoryIndex" : 14,
					"id" : "clean-test::@c593a3635781ae508a1e",
					"jsonFile" : "target-clean-test-Debug-4c694b41df28701182c3.json",
					"name" : "clean-test",
					"projectIndex" : 2
				},
				{
					"directoryIndex" : 14,
					"id" : "coder-test::@c593a3635781ae508a1e",
					"jsonFile" : "target-coder-test-Debug-de09131c2a5ed0157f30.json",
					"name" : "coder-test",
					"projectIndex" : 2
				},
				{
					"directoryIndex" : 14,
					"id" : "coder_test::@c593a3635781ae508a1e",
					"jsonFile" : "target-coder_test-Debug-c30a0e3f68e82f7540a4.json",
					"name" : "coder_test",
					"projectIndex" : 2
				},
				{
					"directoryIndex" : 14,
					"id" : "compile-test::@c593a3635781ae508a1e",
					"jsonFile" : "target-compile-test-Debug-67425ff36cd31b0758f3.json",
					"name" : "compile-test",
					"projectIndex" : 2
				},
				{
					"directoryIndex" : 14,
					"id" : "compile_test::@c593a3635781ae508a1e",
					"jsonFile" : "target-compile_test-Debug-8acf15f214fd0528902d.json",
					"name" : "compile_test",
					"projectIndex" : 2
				},
				{
					"directoryIndex" : 14,
					"id" : "csa-byte-test::@c593a3635781ae508a1e",
					"jsonFile" : "target-csa-byte-test-Debug-e0587690ea9382c76ffb.json",
					"name" : "csa-byte-test",
					"projectIndex" : 2
				},
				{
					"directoryIndex" : 14,
					"id" : "csa-byte-test_100a.txt::@c593a3635781ae508a1e",
					"jsonFile" : "target-csa-byte-test_100a.txt-Debug-f6bb2c3e58eca02ae766.json",
					"name" : "csa-byte-test_100a.txt",
					"projectIndex" : 2
				},
				{
					"directoryIndex" : 14,
					"id" : "csa-byte-test_empty.txt::@c593a3635781ae508a1e",
					"jsonFile" : "target-csa-byte-test_empty.txt-Debug-dfa49e6d13d7c18e183a.json",
					"name" : "csa-byte-test_empty.txt",
					"projectIndex" : 2
				},
				{
					"directoryIndex" : 14,
					"id" : "csa-byte-test_example01.txt::@c593a3635781ae508a1e",
					"jsonFile" : "target-csa-byte-test_example01.txt-Debug-a8cd289973dcbc952e30.json",
					"name" : "csa-byte-test_example01.txt",
					"projectIndex" : 2
				},
				{
					"directoryIndex" : 14,
					"id" : "csa-byte-test_faust.txt::@c593a3635781ae508a1e",
					"jsonFile" : "target-csa-byte-test_faust.txt-Debug-72cc932aaa5d2b244c58.json",
					"name" : "csa-byte-test_faust.txt",
					"projectIndex" : 2
				},
				{
					"directoryIndex" : 14,
					"id" : "csa-byte-test_zarathustra.txt::@c593a3635781ae508a1e",
					"jsonFile" : "target-csa-byte-test_zarathustra.txt-Debug-d800d893da52724b99a7.json",
					"name" : "csa-byte-test_zarathustra.txt",
					"projectIndex" : 2
				},
				{
					"directoryIndex" : 14,
					"id" : "csa-int-test::@c593a3635781ae508a1e",
					"jsonFile" : "target-csa-int-test-Debug-c65b258eb2b7fedda422.json",
					"name" : "csa-int-test",
					"projectIndex" : 2
				},
				{
					"directoryIndex" : 14,
					"id" : "csa-int-test_100a.txt_1::@c593a3635781ae508a1e",
					"jsonFile" : "target-csa-int-test_100a.txt_1-Debug-eb625073de2b6ac15907.json",
					"name" : "csa-int-test_100a.txt_1",
					"projectIndex" : 2
				},
				{
					"directoryIndex" : 14,
					"id" : "csa-int-test_empty.txt_1::@c593a3635781ae508a1e",
					"jsonFile" : "target-csa-int-test_empty.txt_1-Debug-a57b9cc2051b02591e33.json",
					"name" : "csa-int-test_empty.txt_1",
					"projectIndex" : 2
				},
				{
					"directoryIndex" : 14,
					"id" : "csa-int-test_example01.txt_1::@c593a3635781ae508a1e",
					"jsonFile" : "target-csa-int-test_example01.txt_1-Debug-fa279d8ee75c3d3ee23c.json",
					"name" : "csa-int-test_example01.txt_1",
					"projectIndex" : 2
				},
				{
					"directoryIndex" : 14,
					"id" : "csa-int-test_faust.txt_1::@c593a3635781ae508a1e",
					"jsonFile" : "target-csa-int-test_faust.txt_1-Debug-1d3238bc53a3a30d980b.json",
					"name" : "csa-int-test_faust.txt_1",
					"projectIndex" : 2
				},
				{
					"directoryIndex" : 14,
					"id" : "csa-int-test_keeper.int_8::@c593a3635781ae508a1e",
					"jsonFile" : "target-csa-int-test_keeper.int_8-Debug-7c261bd3c3bc599bf2ca.json",
					"name" : "csa-int-test_keeper.int_8",
					"projectIndex" : 2
				},
				{
					"directoryIndex" : 14,
					"id" : "csa-int-test_moby.int_8::@c593a3635781ae508a1e",
					"jsonFile" : "target-csa-int-test_moby.int_8-Debug-7825b3b74cbed8ae17c9.json",
					"name" : "csa-int-test_moby.int_8",
					"projectIndex" : 2
				},
				{
					"directoryIndex" : 14,
					"id" : "csa-int-test_zarathustra.txt_1::@c593a3635781ae508a1e",
					"jsonFile" : "target-csa-int-test_zarathustra.txt_1-Debug-e4624751ff7e9412ad45.json",
					"name" : "csa-int-test_zarathustra.txt_1",
					"projectIndex" : 2
				},
				{
					"directoryIndex" : 14,
					"id" : "csa_byte_test::@c593a3635781ae508a1e",
					"jsonFile" : "target-csa_byte_test-Debug-aeea5b3f60c865f2d114.json",
					"name" : "csa_byte_test",
					"projectIndex" : 2
				},
				{
					"directoryIndex" : 14,
					"id" : "csa_int_test::@c593a3635781ae508a1e",
					"jsonFile" : "target-csa_int_test-Debug-fc127bfd4fb67276cf3f.json",
					"name" : "csa_int_test",
					"projectIndex" : 2
				},
				{
					"directoryIndex" : 14,
					"id" : "cst-byte-test::@c593a3635781ae508a1e",
					"jsonFile" : "target-cst-byte-test-Debug-74d010d6f99f26a8f88b.json",
					"name" : "cst-byte-test",
					"projectIndex" : 2
				},
				{
					"directoryIndex" : 14,
					"id" : "cst-byte-test_100a.txt::@c593a3635781ae508a1e",
					"jsonFile" : "target-cst-byte-test_100a.txt-Debug-be245892e182ba17210d.json",
					"name" : "cst-byte-test_100a.txt",
					"projectIndex" : 2
				},
				{
					"directoryIndex" : 14,
					"id" : "cst-byte-test_empty.txt::@c593a3635781ae508a1e",
					"jsonFile" : "target-cst-byte-test_empty.txt-Debug-4b9c7280a602bf9f2723.json",
					"name" : "cst-byte-test_empty.txt",
					"projectIndex" : 2
				},
				{
					"directoryIndex" : 14,
					"id" : "cst-byte-test_example01.txt::@c593a3635781ae508a1e",
					"jsonFile" : "target-cst-byte-test_example01.txt-Debug-c991f75a46a11f1a3009.json",
					"name" : "cst-byte-test_example01.txt",
					"projectIndex" : 2
				},
				{
					"directoryIndex" : 14,
					"id" : "cst-byte-test_faust.txt::@c593a3635781ae508a1e",
					"jsonFile" : "target-cst-byte-test_faust.txt-Debug-7acfe7fef80df5160637.json",
					"name" : "cst-byte-test_faust.txt",
					"projectIndex" : 2
				},
				{
					"directoryIndex" : 14,
					"id" : "cst-int-test::@c593a3635781ae508a1e",
					"jsonFile" : "target-cst-int-test-Debug-4a9a1385c9ab7fc080f1.json",
					"name" : "cst-int-test",
					"projectIndex" : 2
				},
				{
					"directoryIndex" : 14,
					"id" : "cst-int-test_100a.txt_1::@c593a3635781ae508a1e",
					"jsonFile" : "target-cst-int-test_100a.txt_1-Debug-66206e4cabdd8412eb0e.json",
					"name" : "cst-int-test_100a.txt_1",
					"projectIndex" : 2
				},
				{
					"directoryIndex" : 14,
					"id" : "cst-int-test_empty.txt_1::@c593a3635781ae508a1e",
					"jsonFile" : "target-cst-int-test_empty.txt_1-Debug-b84e2078d69d65f503a9.json",
					"name" : "cst-int-test_empty.txt_1",
					"projectIndex" : 2
				},
				{
					"directoryIndex" : 14,
					"id" : "cst-int-test_example01.txt_1::@c593a3635781ae508a1e",
					"jsonFile" : "target-cst-int-test_example01.txt_1-Debug-0e979390a61d3e533fc9.json",
					"name" : "cst-int-test_example01.txt_1",
					"projectIndex" : 2
				},
				{
					"directoryIndex" : 14,
					"id" : "cst-int-test_faust.txt_1::@c593a3635781ae508a1e",
					"jsonFile" : "target-cst-int-test_faust.txt_1-Debug-7d53116564fe92c2eacd.json",
					"name" : "cst-int-test_faust.txt_1",
					"projectIndex" : 2
				},
				{
					"directoryIndex" : 14,
					"id" : "cst-int-test_int-vec-sa.100000.18.r_0::@c593a3635781ae508a1e",
					"jsonFile" : "target-cst-int-test_int-vec-sa.100000.18.r_0-Debug-e71ca7890f6b6b55dc04.json",
					"name" : "cst-int-test_int-vec-sa.100000.18.r_0",
					"projectIndex" : 2
				},
				{
					"directoryIndex" : 14,
					"id" : "cst-int-test_keeper.int_8::@c593a3635781ae508a1e",
					"jsonFile" : "target-cst-int-test_keeper.int_8-Debug-a966a094e4d4f0df1083.json",
					"name" : "cst-int-test_keeper.int_8",
					"projectIndex" : 2
				},
				{
					"directoryIndex" : 14,
					"id" : "cst-int-test_moby.int_8::@c593a3635781ae508a1e",
					"jsonFile" : "target-cst-int-test_moby.int_8-Debug-660a21c2e47ad6829b7c.json",
					"name" : "cst-int-test_moby.int_8",
					"projectIndex" : 2
				},
				{
					"directoryIndex" : 14,
					"id" : "cst_byte_test::@c593a3635781ae508a1e",
					"jsonFile" : "target-cst_byte_test-Debug-be4fc1cf72fd036f70f5.json",
					"name" : "cst_byte_test",
					"projectIndex" : 2
				},
				{
					"directoryIndex" : 14,
					"id" : "cst_int_test::@c593a3635781ae508a1e",
					"jsonFile" : "target-cst_int_test-Debug-d747faf89ab41fb1d971.json",
					"name" : "cst_int_test",
					"projectIndex" : 2
				},
				{
					"directoryIndex" : 14,
					"id" : "dac-vector-test::@c593a3635781ae508a1e",
					"jsonFile" : "target-dac-vector-test-Debug-8d419951915d33808dad.json",
					"name" : "dac-vector-test",
					"projectIndex" : 2
				},
				{
					"directoryIndex" : 14,
					"id" : "dac_vector_test::@c593a3635781ae508a1e",
					"jsonFile" : "target-dac_vector_test-Debug-eef447a0ab6439b58846.json",
					"name" : "dac_vector_test",
					"projectIndex" : 2
				},
				{
					"directoryIndex" : 18,
					"id" : "divsufsort::@40dc205fb814bcd2e109",
					"jsonFile" : "target-divsufsort-Debug-3c2b5b4d5fdb284a3db5.json",
					"name" : "divsufsort",
					"projectIndex" : 5
				},
				{
					"directoryIndex" : 9,
					"id" : "divsufsort::@36f06ce86c7fe522c77d",
					"jsonFile" : "target-divsufsort-Debug-0a66fe92a744d06e6c00.json",
					"name" : "divsufsort",
					"projectIndex" : 3
				},
				{
					"directoryIndex" : 18,
					"id" : "divsufsort64::@40dc205fb814bcd2e109",
					"jsonFile" : "target-divsufsort64-Debug-beda902ce9b54e26b657.json",
					"name" : "divsufsort64",
					"projectIndex" : 5
				},
				{
					"directoryIndex" : 9,
					"id" : "divsufsort64::@36f06ce86c7fe522c77d",
					"jsonFile" : "target-divsufsort64-Debug-eca464b49cade735cb12.json",
					"name" : "divsufsort64",
					"projectIndex" : 3
				},
				{
					"directoryIndex" : 14,
					"id" : "faust.txt::@c593a3635781ae508a1e",
					"jsonFile" : "target-faust.txt-Debug-5c41a03e0e1eb4d6d837.json",
					"name" : "faust.txt",
					"projectIndex" : 2
				},
				{
					"directoryIndex" : 10,
					"id" : "gtest::@cc55464ead2beace3368",
					"jsonFile" : "target-gtest-Debug-d8bbcd36846a1d1dcf43.json",
					"name" : "gtest",
					"projectIndex" : 4
				},
				{
					"directoryIndex" : 10,
					"id" : "gtest_main::@cc55464ead2beace3368",
					"jsonFile" : "target-gtest_main-Debug-7a0c2e3c2de5a5305a9e.json",
					"name" : "gtest_main",
					"projectIndex" : 4
				},
				{
					"directoryIndex" : 14,
					"id" : "int-vector-buffer-test::@c593a3635781ae508a1e",
					"jsonFile" : "target-int-vector-buffer-test-Debug-4a90d5d0e416392059bb.json",
					"name" : "int-vector-buffer-test",
					"projectIndex" : 2
				},
				{
					"directoryIndex" : 14,
					"id" : "int-vector-mapper-test::@c593a3635781ae508a1e",
					"jsonFile" : "target-int-vector-mapper-test-Debug-cadd05af922f28d86c87.json",
					"name" : "int-vector-mapper-test",
					"projectIndex" : 2
				},
				{
					"directoryIndex" : 14,
					"id" : "int-vector-test::@c593a3635781ae508a1e",
					"jsonFile" : "target-int-vector-test-Debug-c0f6cf79da958eaa9aa3.json",
					"name" : "int-vector-test",
					"projectIndex" : 2
				},
				{
					"directoryIndex" : 14,
					"id" : "int_vector_buffer_test::@c593a3635781ae508a1e",
					"jsonFile" : "target-int_vector_buffer_test-Debug-d6dd0858c5b362dcb437.json",
					"name" : "int_vector_buffer_test",
					"projectIndex" : 2
				},
				{
					"directoryIndex" : 14,
					"id" : "int_vector_generator::@c593a3635781ae508a1e",
					"jsonFile" : "target-int_vector_generator-Debug-c33a80a3ebd3bf18051a.json",
					"name" : "int_vector_generator",
					"projectIndex" : 2
				},
				{
					"directoryIndex" : 14,
					"id" : "int_vector_mapper_test::@c593a3635781ae508a1e",
					"jsonFile" : "target-int_vector_mapper_test-Debug-4c0c9a653c0ae4cc8441.json",
					"name" : "int_vector_mapper_test",
					"projectIndex" : 2
				},
				{
					"directoryIndex" : 14,
					"id" : "int_vector_test::@c593a3635781ae508a1e",
					"jsonFile" : "target-int_vector_test-Debug-db737320b81f8127c7d1.json",
					"name" : "int_vector_test",
					"projectIndex" : 2
				},
				{
					"directoryIndex" : 14,
					"id" : "inv-perm-support-test::@c593a3635781ae508a1e",
					"jsonFile" : "target-inv-perm-support-test-Debug-dad1b47f7dad1fa9bb34.json",
					"name" : "inv-perm-support-test",
					"projectIndex" : 2
				},
				{
					"directoryIndex" : 14,
					"id" : "inv_perm_support_test::@c593a3635781ae508a1e",
					"jsonFile" : "target-inv_perm_support_test-Debug-2fe5fa93b40726c7e0fc.json",
					"name" : "inv_perm_support_test",
					"projectIndex" : 2
				},
				{
					"directoryIndex" : 14,
					"id" : "k2-0.1.0.00.1.0.00.1.0.0::@c593a3635781ae508a1e",
					"jsonFile" : "target-k2-0.1.0.00.1.0.00.1.0.0-Debug-0273c167e6086152435c.json",
					"name" : "k2-0.1.0.00.1.0.00.1.0.0",
					"projectIndex" : 2
				},
				{
					"directoryIndex" : 14,
					"id" : "k2-100.16.r.42100.16.r.23100.8.r.81::@c593a3635781ae508a1e",
					"jsonFile" : "target-k2-100.16.r.42100.16.r.23100.8.r.81-Debug-479567a7f2fd959dd291.json",
					"name" : "k2-100.16.r.42100.16.r.23100.8.r.81",
					"projectIndex" : 2
				},
				{
					"directoryIndex" : 14,
					"id" : "k2-10000.16.r.4210000.16.r.2310000.8.r.81::@c593a3635781ae508a1e",
					"jsonFile" : "target-k2-10000.16.r.4210000.16.r.2310000.8.r.81-Debug-c182abafecc8cf21483e.json",
					"name" : "k2-10000.16.r.4210000.16.r.2310000.8.r.81",
					"projectIndex" : 2
				},
				{
					"directoryIndex" : 14,
					"id" : "k2-100000.39.r.42100000.47.r.23100000.35.r.81::@c593a3635781ae508a1e",
					"jsonFile" : "target-k2-100000.39.r.42100000.47.r.23100000.35.r.81-Debug-858a78cfa9b786a43fe0.json",
					"name" : "k2-100000.39.r.42100000.47.r.23100000.35.r.81",
					"projectIndex" : 2
				},
				{
					"directoryIndex" : 14,
					"id" : "k2-1000000.52.r.421000000.57.r.231000000.45.r.81::@c593a3635781ae508a1e",
					"jsonFile" : "target-k2-1000000.52.r.421000000.57.r.231000000.45.r.81-Debug-463835186d3305ba9067.json",
					"name" : "k2-1000000.52.r.421000000.57.r.231000000.45.r.81",
					"projectIndex" : 2
				},
				{
					"directoryIndex" : 14,
					"id" : "k2-treap-test::@c593a3635781ae508a1e",
					"jsonFile" : "target-k2-treap-test-Debug-3d4543e0569bae98711b.json",
					"name" : "k2-treap-test",
					"projectIndex" : 2
				},
				{
					"directoryIndex" : 14,
					"id" : "k2-treap-test_k2-0.1.0.00.1.0.00.1.0.0::@c593a3635781ae508a1e",
					"jsonFile" : "target-k2-treap-test_k2-0.1.0.00.1.0.00.1.0.0-Debug-240e9e8e9c817d6fe0f6.json",
					"name" : "k2-treap-test_k2-0.1.0.00.1.0.00.1.0.0",
					"projectIndex" : 2
				},
				{
					"directoryIndex" : 14,
					"id" : "k2-treap-test_k2-100.16.r.42100.16.r.23100.8.r.81::@c593a3635781ae508a1e",
					"jsonFile" : "target-k2-treap-test_k2-100.16.r.42100.16.r.23100.8.r.81-Debug-dd659d991eb79fdad0c1.json",
					"name" : "k2-treap-test_k2-100.16.r.42100.16.r.23100.8.r.81",
					"projectIndex" : 2
				},
				{
					"directoryIndex" : 14,
					"id" : "k2-treap-test_k2-10000.16.r.4210000.16.r.2310000.8.r.81::@c593a3635781ae508a1e",
					"jsonFile" : "target-k2-treap-test_k2-10000.16.r.4210000.16.r.2310000.8.r.81-Debug-45638959b40a367f5ddc.json",
					"name" : "k2-treap-test_k2-10000.16.r.4210000.16.r.2310000.8.r.81",
					"projectIndex" : 2
				},
				{
					"directoryIndex" : 14,
					"id" : "k2-treap-test_k2-100000.39.r.42100000.47.r.23100000.35.r.81::@c593a3635781ae508a1e",
					"jsonFile" : "target-k2-treap-test_k2-100000.39.r.42100000.47.r.23100000.35.r.81-Debug-b7f62b4004cce9334fb9.json",
					"name" : "k2-treap-test_k2-100000.39.r.42100000.47.r.23100000.35.r.81",
					"projectIndex" : 2
				},
				{
					"directoryIndex" : 14,
					"id" : "k2-treap-test_k2-1000000.52.r.421000000.57.r.231000000.45.r.81::@c593a3635781ae508a1e",
					"jsonFile" : "target-k2-treap-test_k2-1000000.52.r.421000000.57.r.231000000.45.r.81-Debug-be27faece155ac86989a.json",
					"name" : "k2-treap-test_k2-1000000.52.r.421000000.57.r.231000000.45.r.81",
					"projectIndex" : 2
				},
				{
					"directoryIndex" : 14,
					"id" : "k2-tree-test::@c593a3635781ae508a1e",
					"jsonFile" : "target-k2-tree-test-Debug-9b3fc7796fafc19fd43e.json",
					"name" : "k2-tree-test",
					"projectIndex" : 2
				},
				{
					"directoryIndex" : 14,
					"id" : "k2_treap_test::@c593a3635781ae508a1e",
					"jsonFile" : "target-k2_treap_test-Debug-a266e3ef77ea3dac1154.json",
					"name" : "k2_treap_test",
					"projectIndex" : 2
				},
				{
					"directoryIndex" : 14,
					"id" : "k2_tree_test::@c593a3635781ae508a1e",
					"jsonFile" : "target-k2_tree_test-Debug-53fa80e99094e92c434c.json",
					"name" : "k2_tree_test",
					"projectIndex" : 2
				},
				{
					"directoryIndex" : 14,
					"id" : "lcp-construct-test::@c593a3635781ae508a1e",
					"jsonFile" : "target-lcp-construct-test-Debug-cee93508cdf0556f3276.json",
					"name" : "lcp-construct-test",
					"projectIndex" : 2
				},
				{
					"directoryIndex" : 14,
					"id" : "lcp-construct-test_100a.txt::@c593a3635781ae508a1e",
					"jsonFile" : "target-lcp-construct-test_100a.txt-Debug-0194998e395137317a39.json",
					"name" : "lcp-construct-test_100a.txt",
					"projectIndex" : 2
				},
				{
					"directoryIndex" : 14,
					"id" : "lcp-construct-test_empty.txt::@c593a3635781ae508a1e",
					"jsonFile" : "target-lcp-construct-test_empty.txt-Debug-3c830ebc7edbc59ccd39.json",
					"name" : "lcp-construct-test_empty.txt",
					"projectIndex" : 2
				},
				{
					"directoryIndex" : 14,
					"id" : "lcp-construct-test_example01.txt::@c593a3635781ae508a1e",
					"jsonFile" : "target-lcp-construct-test_example01.txt-Debug-ce8e3b5a36f1182cedcb.json",
					"name" : "lcp-construct-test_example01.txt",
					"projectIndex" : 2
				},
				{
					"directoryIndex" : 14,
					"id" : "lcp-construct-test_faust.txt::@c593a3635781ae508a1e",
					"jsonFile" : "target-lcp-construct-test_faust.txt-Debug-c0d8f3839bf8130bcae2.json",
					"name" : "lcp-construct-test_faust.txt",
					"projectIndex" : 2
				},
				{
					"directoryIndex" : 14,
					"id" : "lcp-construct-test_zarathustra.txt::@c593a3635781ae508a1e",
					"jsonFile" : "target-lcp-construct-test_zarathustra.txt-Debug-b4b568eb494a894fb886.json",
					"name" : "lcp-construct-test_zarathustra.txt",
					"projectIndex" : 2
				},
				{
					"directoryIndex" : 14,
					"id" : "lcp_construct_test::@c593a3635781ae508a1e",
					"jsonFile" : "target-lcp_construct_test-Debug-08ccdf6bb0fee401a629.json",
					"name" : "lcp_construct_test",
					"projectIndex" : 2
				},
				{
					"directoryIndex" : 14,
					"id" : "moby.int::@c593a3635781ae508a1e",
					"jsonFile" : "target-moby.int-Debug-1b49cbdc1f4ebacd5609.json",
					"name" : "moby.int",
					"projectIndex" : 2
				},
				{
					"directoryIndex" : 14,
					"id" : "nn-dict-dynamic-test::@c593a3635781ae508a1e",
					"jsonFile" : "target-nn-dict-dynamic-test-Debug-3d24b6aa99b6b092793a.json",
					"name" : "nn-dict-dynamic-test",
					"projectIndex" : 2
				},
				{
					"directoryIndex" : 14,
					"id" : "nn_dict_dynamic_test::@c593a3635781ae508a1e",
					"jsonFile" : "target-nn_dict_dynamic_test-Debug-5a4efc6df3ec1fe745ee.json",
					"name" : "nn_dict_dynamic_test",
					"projectIndex" : 2
				},
				{
					"directoryIndex" : 14,
					"id" : "rank-support-test::@c593a3635781ae508a1e",
					"jsonFile" : "target-rank-support-test-Debug-63681a5eb69969df5917.json",
					"name" : "rank-support-test",
					"projectIndex" : 2
				},
				{
					"directoryIndex" : 14,
					"id" : "rank-support-test_bit-vec.CRAFTED-32::@c593a3635781ae508a1e",
					"jsonFile" : "target-rank-support-test_bit-vec.CRAFTED-32-Debug-c9e6dbd87c7383e554f5.json",
					"name" : "rank-support-test_bit-vec.CRAFTED-32",
					"projectIndex" : 2
				},
				{
					"directoryIndex" : 14,
					"id" : "rank-support-test_bit-vec.CRAFTED-BLOCK-0::@c593a3635781ae508a1e",
					"jsonFile" : "target-rank-support-test_bit-vec.CRAFTED-BLOCK-0-Debug-b3cd7ed85c7944813f75.json",
					"name" : "rank-support-test_bit-vec.CRAFTED-BLOCK-0",
					"projectIndex" : 2
				},
				{
					"directoryIndex" : 14,
					"id" : "rank-support-test_bit-vec.CRAFTED-BLOCK-1::@c593a3635781ae508a1e",
					"jsonFile" : "target-rank-support-test_bit-vec.CRAFTED-BLOCK-1-Debug-3c89ac5c6d290c807c30.json",
					"name" : "rank-support-test_bit-vec.CRAFTED-BLOCK-1",
					"projectIndex" : 2
				},
				{
					"directoryIndex" : 14,
					"id" : "rank-support-test_bit-vec.CRAFTED-MAT-SELECT::@c593a3635781ae508a1e",
					"jsonFile" : "target-rank-support-test_bit-vec.CRAFTED-MAT-SELECT-Debug-c3295e8a84437ad729fc.json",
					"name" : "rank-support-test_bit-vec.CRAFTED-MAT-SELECT",
					"projectIndex" : 2
				},
				{
					"directoryIndex" : 14,
					"id" : "rank-support-test_bit-vec.CRAFTED-SPARSE-0::@c593a3635781ae508a1e",
					"jsonFile" : "target-rank-support-test_bit-vec.CRAFTED-SPARSE-0-Debug-9be0d436e9aa4e7098ae.json",
					"name" : "rank-support-test_bit-vec.CRAFTED-SPARSE-0",
					"projectIndex" : 2
				},
				{
					"directoryIndex" : 14,
					"id" : "rank-support-test_bit-vec.CRAFTED-SPARSE-1::@c593a3635781ae508a1e",
					"jsonFile" : "target-rank-support-test_bit-vec.CRAFTED-SPARSE-1-Debug-295f1b88ad29bc1cea54.json",
					"name" : "rank-support-test_bit-vec.CRAFTED-SPARSE-1",
					"projectIndex" : 2
				},
				{
					"directoryIndex" : 14,
					"id" : "rank-support-test_int-vec.0.1.0::@c593a3635781ae508a1e",
					"jsonFile" : "target-rank-support-test_int-vec.0.1.0-Debug-63c338f4de512fadb327.json",
					"name" : "rank-support-test_int-vec.0.1.0",
					"projectIndex" : 2
				},
				{
					"directoryIndex" : 14,
					"id" : "rank-support-test_int-vec.1.1.0::@c593a3635781ae508a1e",
					"jsonFile" : "target-rank-support-test_int-vec.1.1.0-Debug-24238768fe99fad0156e.json",
					"name" : "rank-support-test_int-vec.1.1.0",
					"projectIndex" : 2
				},
				{
					"directoryIndex" : 14,
					"id" : "rank-support-test_int-vec.10.1.0::@c593a3635781ae508a1e",
					"jsonFile" : "target-rank-support-test_int-vec.10.1.0-Debug-0bf9a9023e5ef7983550.json",
					"name" : "rank-support-test_int-vec.10.1.0",
					"projectIndex" : 2
				},
				{
					"directoryIndex" : 14,
					"id" : "rank-support-test_int-vec.1000000.1.0::@c593a3635781ae508a1e",
					"jsonFile" : "target-rank-support-test_int-vec.1000000.1.0-Debug-1d45124d4a7917cfe453.json",
					"name" : "rank-support-test_int-vec.1000000.1.0",
					"projectIndex" : 2
				},
				{
					"directoryIndex" : 14,
					"id" : "rank-support-test_int-vec.1000000.1.1::@c593a3635781ae508a1e",
					"jsonFile" : "target-rank-support-test_int-vec.1000000.1.1-Debug-a44d76d40b1084b47595.json",
					"name" : "rank-support-test_int-vec.1000000.1.1",
					"projectIndex" : 2
				},
				{
					"directoryIndex" : 14,
					"id" : "rank-support-test_int-vec.1000000.1.r.815::@c593a3635781ae508a1e",
					"jsonFile" : "target-rank-support-test_int-vec.1000000.1.r.815-Debug-290606e12accf901ad2f.json",
					"name" : "rank-support-test_int-vec.1000000.1.r.815",
					"projectIndex" : 2
				},
				{
					"directoryIndex" : 14,
					"id" : "rank-support-test_int-vec.1024.1.r.898::@c593a3635781ae508a1e",
					"jsonFile" : "target-rank-support-test_int-vec.1024.1.r.898-Debug-d9efe640bbb0bd44526b.json",
					"name" : "rank-support-test_int-vec.1024.1.r.898",
					"projectIndex" : 2
				},
				{
					"directoryIndex" : 14,
					"id" : "rank-support-test_int-vec.11.1.1::@c593a3635781ae508a1e",
					"jsonFile" : "target-rank-support-test_int-vec.11.1.1-Debug-bce424eca116234acef5.json",
					"name" : "rank-support-test_int-vec.11.1.1",
					"projectIndex" : 2
				},
				{
					"directoryIndex" : 14,
					"id" : "rank-support-test_int-vec.12.1.0::@c593a3635781ae508a1e",
					"jsonFile" : "target-rank-support-test_int-vec.12.1.0-Debug-b2f63981b4f96d408d60.json",
					"name" : "rank-support-test_int-vec.12.1.0",
					"projectIndex" : 2
				},
				{
					"directoryIndex" : 14,
					"id" : "rank-support-test_int-vec.128.1.r.73::@c593a3635781ae508a1e",
					"jsonFile" : "target-rank-support-test_int-vec.128.1.r.73-Debug-5efd6b73b2970529e82b.json",
					"name" : "rank-support-test_int-vec.128.1.r.73",
					"projectIndex" : 2
				},
				{
					"directoryIndex" : 14,
					"id" : "rank-support-test_int-vec.13.1.1::@c593a3635781ae508a1e",
					"jsonFile" : "target-rank-support-test_int-vec.13.1.1-Debug-115a9762eeb128abf860.json",
					"name" : "rank-support-test_int-vec.13.1.1",
					"projectIndex" : 2
				},
				{
					"directoryIndex" : 14,
					"id" : "rank-support-test_int-vec.14.1.0::@c593a3635781ae508a1e",
					"jsonFile" : "target-rank-support-test_int-vec.14.1.0-Debug-d6216cab99ad626ec978.json",
					"name" : "rank-support-test_int-vec.14.1.0",
					"projectIndex" : 2
				},
				{
					"directoryIndex" : 14,
					"id" : "rank-support-test_int-vec.15.1.1::@c593a3635781ae508a1e",
					"jsonFile" : "target-rank-support-test_int-vec.15.1.1-Debug-cd727a550ccc2f95e65b.json",
					"name" : "rank-support-test_int-vec.15.1.1",
					"projectIndex" : 2
				},
				{
					"directoryIndex" : 14,
					"id" : "rank-support-test_int-vec.16.1.r.42::@c593a3635781ae508a1e",
					"jsonFile" : "target-rank-support-test_int-vec.16.1.r.42-Debug-facb5d8656ceaf360364.json",
					"name" : "rank-support-test_int-vec.16.1.r.42",
					"projectIndex" : 2
				},
				{
					"directoryIndex" : 14,
					"id" : "rank-support-test_int-vec.2048.1.r.5432::@c593a3635781ae508a1e",
					"jsonFile" : "target-rank-support-test_int-vec.2048.1.r.5432-Debug-a55ab334dde9a5d3cf74.json",
					"name" : "rank-support-test_int-vec.2048.1.r.5432",
					"projectIndex" : 2
				},
				{
					"directoryIndex" : 14,
					"id" : "rank-support-test_int-vec.256.1.r.4887::@c593a3635781ae508a1e",
					"jsonFile" : "target-rank-support-test_int-vec.256.1.r.4887-Debug-772f38e273bd75df57bc.json",
					"name" : "rank-support-test_int-vec.256.1.r.4887",
					"projectIndex" : 2
				},
				{
					"directoryIndex" : 14,
					"id" : "rank-support-test_int-vec.32.1.r.111::@c593a3635781ae508a1e",
					"jsonFile" : "target-rank-support-test_int-vec.32.1.r.111-Debug-6979e68e3ef8273a955c.json",
					"name" : "rank-support-test_int-vec.32.1.r.111",
					"projectIndex" : 2
				},
				{
					"directoryIndex" : 14,
					"id" : "rank-support-test_int-vec.4096.1.r.793::@c593a3635781ae508a1e",
					"jsonFile" : "target-rank-support-test_int-vec.4096.1.r.793-Debug-022dbe6dfd15d02b320f.json",
					"name" : "rank-support-test_int-vec.4096.1.r.793",
					"projectIndex" : 2
				},
				{
					"directoryIndex" : 14,
					"id" : "rank-support-test_int-vec.512.1.r.432::@c593a3635781ae508a1e",
					"jsonFile" : "target-rank-support-test_int-vec.512.1.r.432-Debug-dd43636bf7325e5e9d79.json",
					"name" : "rank-support-test_int-vec.512.1.r.432",
					"projectIndex" : 2
				},
				{
					"directoryIndex" : 14,
					"id" : "rank-support-test_int-vec.64.1.r.222::@c593a3635781ae508a1e",
					"jsonFile" : "target-rank-support-test_int-vec.64.1.r.222-Debug-7e9644637bd9043fa0e4.json",
					"name" : "rank-support-test_int-vec.64.1.r.222",
					"projectIndex" : 2
				},
				{
					"directoryIndex" : 14,
					"id" : "rank-support-test_int-vec.7.1.1::@c593a3635781ae508a1e",
					"jsonFile" : "target-rank-support-test_int-vec.7.1.1-Debug-45b4e2cb8a9eecd8e885.json",
					"name" : "rank-support-test_int-vec.7.1.1",
					"projectIndex" : 2
				},
				{
					"directoryIndex" : 14,
					"id" : "rank-support-test_int-vec.8.1.0::@c593a3635781ae508a1e",
					"jsonFile" : "target-rank-support-test_int-vec.8.1.0-Debug-21e016f342e364c30a22.json",
					"name" : "rank-support-test_int-vec.8.1.0",
					"projectIndex" : 2
				},
				{
					"directoryIndex" : 14,
					"id" : "rank-support-test_int-vec.8.1.r.17::@c593a3635781ae508a1e",
					"jsonFile" : "target-rank-support-test_int-vec.8.1.r.17-Debug-b3605039d379caf96a25.json",
					"name" : "rank-support-test_int-vec.8.1.r.17",
					"projectIndex" : 2
				},
				{
					"directoryIndex" : 14,
					"id" : "rank-support-test_int-vec.8192.1.r.1043::@c593a3635781ae508a1e",
					"jsonFile" : "target-rank-support-test_int-vec.8192.1.r.1043-Debug-5a751ada269404a6bfaa.json",
					"name" : "rank-support-test_int-vec.8192.1.r.1043",
					"projectIndex" : 2
				},
				{
					"directoryIndex" : 14,
					"id" : "rank-support-test_int-vec.9.1.1::@c593a3635781ae508a1e",
					"jsonFile" : "target-rank-support-test_int-vec.9.1.1-Debug-23ae6ea393b243dacda8.json",
					"name" : "rank-support-test_int-vec.9.1.1",
					"projectIndex" : 2
				},
				{
					"directoryIndex" : 14,
					"id" : "rank_support_test::@c593a3635781ae508a1e",
					"jsonFile" : "target-rank_support_test-Debug-013780913bef74140639.json",
					"name" : "rank_support_test",
					"projectIndex" : 2
				},
				{
					"directoryIndex" : 0,
					"id" : "rapid_check::@6890427a1f51a3e7e1df",
					"jsonFile" : "target-rapid_check-Debug-f1f367d3ae79bb1ce107.json",
					"name" : "rapid_check",
					"projectIndex" : 0
				},
				{
					"directoryIndex" : 1,
					"id" : "rapidcheck::@6d0e2ab76300535f17ff",
					"jsonFile" : "target-rapidcheck-Debug-514e5a25162691023b2a.json",
					"name" : "rapidcheck",
					"projectIndex" : 1
				},
				{
					"directoryIndex" : 14,
					"id" : "replace_int_vector_value::@c593a3635781ae508a1e",
					"jsonFile" : "target-replace_int_vector_value-Debug-524dee3989d294149dbb.json",
					"name" : "replace_int_vector_value",
					"projectIndex" : 2
				},
				{
					"directoryIndex" : 14,
					"id" : "rmq-test::@c593a3635781ae508a1e",
					"jsonFile" : "target-rmq-test-Debug-5e1b9dafa1bc6fbfa97e.json",
					"name" : "rmq-test",
					"projectIndex" : 2
				},
				{
					"directoryIndex" : 14,
					"id" : "rmq-test_int-vec.0.1.0::@c593a3635781ae508a1e",
					"jsonFile" : "target-rmq-test_int-vec.0.1.0-Debug-5d522795511fafefdd94.json",
					"name" : "rmq-test_int-vec.0.1.0",
					"projectIndex" : 2
				},
				{
					"directoryIndex" : 14,
					"id" : "rmq-test_int-vec.1.64.42::@c593a3635781ae508a1e",
					"jsonFile" : "target-rmq-test_int-vec.1.64.42-Debug-2c9ef2496a58d8b3ab20.json",
					"name" : "rmq-test_int-vec.1.64.42",
					"projectIndex" : 2
				},
				{
					"directoryIndex" : 14,
					"id" : "rmq-test_int-vec.1000000.32.i.42::@c593a3635781ae508a1e",
					"jsonFile" : "target-rmq-test_int-vec.1000000.32.i.42-Debug-ce7730db25d7751148ef.json",
					"name" : "rmq-test_int-vec.1000000.32.i.42",
					"projectIndex" : 2
				},
				{
					"directoryIndex" : 14,
					"id" : "rmq-test_int-vec.1000000.64.i::@c593a3635781ae508a1e",
					"jsonFile" : "target-rmq-test_int-vec.1000000.64.i-Debug-79384795571ea7394a7e.json",
					"name" : "rmq-test_int-vec.1000000.64.i",
					"projectIndex" : 2
				},
				{
					"directoryIndex" : 14,
					"id" : "rmq-test_int-vec.1000000.64.i.17::@c593a3635781ae508a1e",
					"jsonFile" : "target-rmq-test_int-vec.1000000.64.i.17-Debug-7098a5eaf0b61770c18e.json",
					"name" : "rmq-test_int-vec.1000000.64.i.17",
					"projectIndex" : 2
				},
				{
					"directoryIndex" : 14,
					"id" : "rmq_test::@c593a3635781ae508a1e",
					"jsonFile" : "target-rmq_test-Debug-b3a6a81752fd987ca034.json",
					"name" : "rmq_test",
					"projectIndex" : 2
				},
				{
					"directoryIndex" : 14,
					"id" : "sa-construct-test::@c593a3635781ae508a1e",
					"jsonFile" : "target-sa-construct-test-Debug-8d7349cb8c4f0bcd38b8.json",
					"name" : "sa-construct-test",
					"projectIndex" : 2
				},
				{
					"directoryIndex" : 14,
					"id" : "sa-construct-test_100a.txt::@c593a3635781ae508a1e",
					"jsonFile" : "target-sa-construct-test_100a.txt-Debug-4978981022e63bb34b86.json",
					"name" : "sa-construct-test_100a.txt",
					"projectIndex" : 2
				},
				{
					"directoryIndex" : 14,
					"id" : "sa-construct-test_empty.txt::@c593a3635781ae508a1e",
					"jsonFile" : "target-sa-construct-test_empty.txt-Debug-644eba87695cefc94949.json",
					"name" : "sa-construct-test_empty.txt",
					"projectIndex" : 2
				},
				{
					"directoryIndex" : 14,
					"id" : "sa-construct-test_example01.txt::@c593a3635781ae508a1e",
					"jsonFile" : "target-sa-construct-test_example01.txt-Debug-d70afd69e6148f9eb40f.json",
					"name" : "sa-construct-test_example01.txt",
					"projectIndex" : 2
				},
				{
					"directoryIndex" : 14,
					"id" : "sa-construct-test_faust.txt::@c593a3635781ae508a1e",
					"jsonFile" : "target-sa-construct-test_faust.txt-Debug-ee2859d3dbd776e4e833.json",
					"name" : "sa-construct-test_faust.txt",
					"projectIndex" : 2
				},
				{
					"directoryIndex" : 14,
					"id" : "sa-construct-test_one_byte.txt::@c593a3635781ae508a1e",
					"jsonFile" : "target-sa-construct-test_one_byte.txt-Debug-ada5527ccf3043081711.json",
					"name" : "sa-construct-test_one_byte.txt",
					"projectIndex" : 2
				},
				{
					"directoryIndex" : 14,
					"id" : "sa-construct-test_zarathustra.txt::@c593a3635781ae508a1e",
					"jsonFile" : "target-sa-construct-test_zarathustra.txt-Debug-e9c0dd3947fecb968b10.json",
					"name" : "sa-construct-test_zarathustra.txt",
					"projectIndex" : 2
				},
				{
					"directoryIndex" : 14,
					"id" : "sa_construct_test::@c593a3635781ae508a1e",
					"jsonFile" : "target-sa_construct_test-Debug-de218f11cc699b7e7886.json",
					"name" : "sa_construct_test",
					"projectIndex" : 2
				},
				{
					"directoryIndex" : 14,
					"id" : "sd-vector-test::@c593a3635781ae508a1e",
					"jsonFile" : "target-sd-vector-test-Debug-833eb7a53ac4369eb192.json",
					"name" : "sd-vector-test",
					"projectIndex" : 2
				},
				{
					"directoryIndex" : 14,
					"id" : "sd_vector_test::@c593a3635781ae508a1e",
					"jsonFile" : "target-sd_vector_test-Debug-f21fae8db94979a108a2.json",
					"name" : "sd_vector_test",
					"projectIndex" : 2
				},
				{
					"directoryIndex" : 13,
					"id" : "sdsl::@eaa4b8ea0b001e770a0e",
					"jsonFile" : "target-sdsl-Debug-6f11862c5f8f7174378b.json",
					"name" : "sdsl",
					"projectIndex" : 2
				},
				{
					"directoryIndex" : 14,
					"id" : "search-bidirectional-test::@c593a3635781ae508a1e",
					"jsonFile" : "target-search-bidirectional-test-Debug-a64fe59f14583df79554.json",
					"name" : "search-bidirectional-test",
					"projectIndex" : 2
				},
				{
					"directoryIndex" : 14,
					"id" : "search-bidirectional-test_100a.txt::@c593a3635781ae508a1e",
					"jsonFile" : "target-search-bidirectional-test_100a.txt-Debug-43d8ec16faa2e2f82bdf.json",
					"name" : "search-bidirectional-test_100a.txt",
					"projectIndex" : 2
				},
				{
					"directoryIndex" : 14,
					"id" : "search-bidirectional-test_empty.txt::@c593a3635781ae508a1e",
					"jsonFile" : "target-search-bidirectional-test_empty.txt-Debug-7774574e78a24da28bc9.json",
					"name" : "search-bidirectional-test_empty.txt",
					"projectIndex" : 2
				},
				{
					"directoryIndex" : 14,
					"id" : "search-bidirectional-test_example01.txt::@c593a3635781ae508a1e",
					"jsonFile" : "target-search-bidirectional-test_example01.txt-Debug-ef703d47cd31fbe381b5.json",
					"name" : "search-bidirectional-test_example01.txt",
					"projectIndex" : 2
				},
				{
					"directoryIndex" : 14,
					"id" : "search-bidirectional-test_faust.txt::@c593a3635781ae508a1e",
					"jsonFile" : "target-search-bidirectional-test_faust.txt-Debug-a173fc212d2fa33b8673.json",
					"name" : "search-bidirectional-test_faust.txt",
					"projectIndex" : 2
				},
				{
					"directoryIndex" : 14,
					"id" : "search-bidirectional-test_zarathustra.txt::@c593a3635781ae508a1e",
					"jsonFile" : "target-search-bidirectional-test_zarathustra.txt-Debug-6d0fd8998059193b6a6a.json",
					"name" : "search-bidirectional-test_zarathustra.txt",
					"projectIndex" : 2
				},
				{
					"directoryIndex" : 14,
					"id" : "search_bidirectional_test::@c593a3635781ae508a1e",
					"jsonFile" : "target-search_bidirectional_test-Debug-c68c98ef70de41e990c3.json",
					"name" : "search_bidirectional_test",
					"projectIndex" : 2
				},
				{
					"directoryIndex" : 14,
					"id" : "select-support-test::@c593a3635781ae508a1e",
					"jsonFile" : "target-select-support-test-Debug-97e2f48fc92a5010c593.json",
					"name" : "select-support-test",
					"projectIndex" : 2
				},
				{
					"directoryIndex" : 14,
					"id" : "select-support-test_bit-vec.CRAFTED-32::@c593a3635781ae508a1e",
					"jsonFile" : "target-select-support-test_bit-vec.CRAFTED-32-Debug-f3f373de4237aa5db7dc.json",
					"name" : "select-support-test_bit-vec.CRAFTED-32",
					"projectIndex" : 2
				},
				{
					"directoryIndex" : 14,
					"id" : "select-support-test_bit-vec.CRAFTED-BLOCK-0::@c593a3635781ae508a1e",
					"jsonFile" : "target-select-support-test_bit-vec.CRAFTED-BLOCK-0-Debug-405c4ca37317899d503e.json",
					"name" : "select-support-test_bit-vec.CRAFTED-BLOCK-0",
					"projectIndex" : 2
				},
				{
					"directoryIndex" : 14,
					"id" : "select-support-test_bit-vec.CRAFTED-BLOCK-1::@c593a3635781ae508a1e",
					"jsonFile" : "target-select-support-test_bit-vec.CRAFTED-BLOCK-1-Debug-f17d5eba5e96cae90fc2.json",
					"name" : "select-support-test_bit-vec.CRAFTED-BLOCK-1",
					"projectIndex" : 2
				},
				{
					"directoryIndex" : 14,
					"id" : "select-support-test_bit-vec.CRAFTED-MAT-SELECT::@c593a3635781ae508a1e",
					"jsonFile" : "target-select-support-test_bit-vec.CRAFTED-MAT-SELECT-Debug-9ef39ff36956644415b6.json",
					"name" : "select-support-test_bit-vec.CRAFTED-MAT-SELECT",
					"projectIndex" : 2
				},
				{
					"directoryIndex" : 14,
					"id" : "select-support-test_bit-vec.CRAFTED-SPARSE-0::@c593a3635781ae508a1e",
					"jsonFile" : "target-select-support-test_bit-vec.CRAFTED-SPARSE-0-Debug-afd1de5822a7562b4b71.json",
					"name" : "select-support-test_bit-vec.CRAFTED-SPARSE-0",
					"projectIndex" : 2
				},
				{
					"directoryIndex" : 14,
					"id" : "select-support-test_bit-vec.CRAFTED-SPARSE-1::@c593a3635781ae508a1e",
					"jsonFile" : "target-select-support-test_bit-vec.CRAFTED-SPARSE-1-Debug-ae4b405d6015d31fad45.json",
					"name" : "select-support-test_bit-vec.CRAFTED-SPARSE-1",
					"projectIndex" : 2
				},
				{
					"directoryIndex" : 14,
					"id" : "select-support-test_int-vec.0.1.0::@c593a3635781ae508a1e",
					"jsonFile" : "target-select-support-test_int-vec.0.1.0-Debug-73947047ffefebc3c6e9.json",
					"name" : "select-support-test_int-vec.0.1.0",
					"projectIndex" : 2
				},
				{
					"directoryIndex" : 14,
					"id" : "select-support-test_int-vec.1.1.0::@c593a3635781ae508a1e",
					"jsonFile" : "target-select-support-test_int-vec.1.1.0-Debug-8f639b8554c3c586db8e.json",
					"name" : "select-support-test_int-vec.1.1.0",
					"projectIndex" : 2
				},
				{
					"directoryIndex" : 14,
					"id" : "select-support-test_int-vec.10.1.0::@c593a3635781ae508a1e",
					"jsonFile" : "target-select-support-test_int-vec.10.1.0-Debug-26595a5371973c5d07ec.json",
					"name" : "select-support-test_int-vec.10.1.0",
					"projectIndex" : 2
				},
				{
					"directoryIndex" : 14,
					"id" : "select-support-test_int-vec.1000000.1.0::@c593a3635781ae508a1e",
					"jsonFile" : "target-select-support-test_int-vec.1000000.1.0-Debug-2567cc096b66f0d41697.json",
					"name" : "select-support-test_int-vec.1000000.1.0",
					"projectIndex" : 2
				},
				{
					"directoryIndex" : 14,
					"id" : "select-support-test_int-vec.1000000.1.1::@c593a3635781ae508a1e",
					"jsonFile" : "target-select-support-test_int-vec.1000000.1.1-Debug-4b07d98f8aafd269a592.json",
					"name" : "select-support-test_int-vec.1000000.1.1",
					"projectIndex" : 2
				},
				{
					"directoryIndex" : 14,
					"id" : "select-support-test_int-vec.1000000.1.r.815::@c593a3635781ae508a1e",
					"jsonFile" : "target-select-support-test_int-vec.1000000.1.r.815-Debug-34dabe092803b644c889.json",
					"name" : "select-support-test_int-vec.1000000.1.r.815",
					"projectIndex" : 2
				},
				{
					"directoryIndex" : 14,
					"id" : "select-support-test_int-vec.1024.1.r.898::@c593a3635781ae508a1e",
					"jsonFile" : "target-select-support-test_int-vec.1024.1.r.898-Debug-9402f49fff72132d7f91.json",
					"name" : "select-support-test_int-vec.1024.1.r.898",
					"projectIndex" : 2
				},
				{
					"directoryIndex" : 14,
					"id" : "select-support-test_int-vec.11.1.1::@c593a3635781ae508a1e",
					"jsonFile" : "target-select-support-test_int-vec.11.1.1-Debug-12609c6e7213b8cc62ee.json",
					"name" : "select-support-test_int-vec.11.1.1",
					"projectIndex" : 2
				},
				{
					"directoryIndex" : 14,
					"id" : "select-support-test_int-vec.12.1.0::@c593a3635781ae508a1e",
					"jsonFile" : "target-select-support-test_int-vec.12.1.0-Debug-c33ccf80bcdd45084cf8.json",
					"name" : "select-support-test_int-vec.12.1.0",
					"projectIndex" : 2
				},
				{
					"directoryIndex" : 14,
					"id" : "select-support-test_int-vec.128.1.r.73::@c593a3635781ae508a1e",
					"jsonFile" : "target-select-support-test_int-vec.128.1.r.73-Debug-ea45e9a9cbebed3be3c9.json",
					"name" : "select-support-test_int-vec.128.1.r.73",
					"projectIndex" : 2
				},
				{
					"directoryIndex" : 14,
					"id" : "select-support-test_int-vec.13.1.1::@c593a3635781ae508a1e",
					"jsonFile" : "target-select-support-test_int-vec.13.1.1-Debug-37294935987a0e5959b9.json",
					"name" : "select-support-test_int-vec.13.1.1",
					"projectIndex" : 2
				},
				{
					"directoryIndex" : 14,
					"id" : "select-support-test_int-vec.14.1.0::@c593a3635781ae508a1e",
					"jsonFile" : "target-select-support-test_int-vec.14.1.0-Debug-473893df0962aa1b980f.json",
					"name" : "select-support-test_int-vec.14.1.0",
					"projectIndex" : 2
				},
				{
					"directoryIndex" : 14,
					"id" : "select-support-test_int-vec.15.1.1::@c593a3635781ae508a1e",
					"jsonFile" : "target-select-support-test_int-vec.15.1.1-Debug-06304ca1203950aa6141.json",
					"name" : "select-support-test_int-vec.15.1.1",
					"projectIndex" : 2
				},
				{
					"directoryIndex" : 14,
					"id" : "select-support-test_int-vec.16.1.r.42::@c593a3635781ae508a1e",
					"jsonFile" : "target-select-support-test_int-vec.16.1.r.42-Debug-58941ebf6c4d173a9529.json",
					"name" : "select-support-test_int-vec.16.1.r.42",
					"projectIndex" : 2
				},
				{
					"directoryIndex" : 14,
					"id" : "select-support-test_int-vec.2048.1.r.5432::@c593a3635781ae508a1e",
					"jsonFile" : "target-select-support-test_int-vec.2048.1.r.5432-Debug-4cbbb717794097bcf1dc.json",
					"name" : "select-support-test_int-vec.2048.1.r.5432",
					"projectIndex" : 2
				},
				{
					"directoryIndex" : 14,
					"id" : "select-support-test_int-vec.256.1.r.4887::@c593a3635781ae508a1e",
					"jsonFile" : "target-select-support-test_int-vec.256.1.r.4887-Debug-a3ca50f1886be93f2900.json",
					"name" : "select-support-test_int-vec.256.1.r.4887",
					"projectIndex" : 2
				},
				{
					"directoryIndex" : 14,
					"id" : "select-support-test_int-vec.32.1.r.111::@c593a3635781ae508a1e",
					"jsonFile" : "target-select-support-test_int-vec.32.1.r.111-Debug-08ccedb5a43de4054b3f.json",
					"name" : "select-support-test_int-vec.32.1.r.111",
					"projectIndex" : 2
				},
				{
					"directoryIndex" : 14,
					"id" : "select-support-test_int-vec.4096.1.r.793::@c593a3635781ae508a1e",
					"jsonFile" : "target-select-support-test_int-vec.4096.1.r.793-Debug-12c8a0a3c4a053229602.json",
					"name" : "select-support-test_int-vec.4096.1.r.793",
					"projectIndex" : 2
				},
				{
					"directoryIndex" : 14,
					"id" : "select-support-test_int-vec.512.1.r.432::@c593a3635781ae508a1e",
					"jsonFile" : "target-select-support-test_int-vec.512.1.r.432-Debug-1d3bb57af5077fc480db.json",
					"name" : "select-support-test_int-vec.512.1.r.432",
					"projectIndex" : 2
				},
				{
					"directoryIndex" : 14,
					"id" : "select-support-test_int-vec.64.1.r.222::@c593a3635781ae508a1e",
					"jsonFile" : "target-select-support-test_int-vec.64.1.r.222-Debug-6cd063e5b0d5a8730f29.json",
					"name" : "select-support-test_int-vec.64.1.r.222",
					"projectIndex" : 2
				},
				{
					"directoryIndex" : 14,
					"id" : "select-support-test_int-vec.7.1.1::@c593a3635781ae508a1e",
					"jsonFile" : "target-select-support-test_int-vec.7.1.1-Debug-9efd9ae2f644844de77b.json",
					"name" : "select-support-test_int-vec.7.1.1",
					"projectIndex" : 2
				},
				{
					"directoryIndex" : 14,
					"id" : "select-support-test_int-vec.8.1.0::@c593a3635781ae508a1e",
					"jsonFile" : "target-select-support-test_int-vec.8.1.0-Debug-762581a581238d136332.json",
					"name" : "select-support-test_int-vec.8.1.0",
					"projectIndex" : 2
				},
				{
					"directoryIndex" : 14,
					"id" : "select-support-test_int-vec.8.1.r.17::@c593a3635781ae508a1e",
					"jsonFile" : "target-select-support-test_int-vec.8.1.r.17-Debug-f7bfc68476f7ef0f41c2.json",
					"name" : "select-support-test_int-vec.8.1.r.17",
					"projectIndex" : 2
				},
				{
					"directoryIndex" : 14,
					"id" : "select-support-test_int-vec.8192.1.r.1043::@c593a3635781ae508a1e",
					"jsonFile" : "target-select-support-test_int-vec.8192.1.r.1043-Debug-6dcf28d029001b1e15eb.json",
					"name" : "select-support-test_int-vec.8192.1.r.1043",
					"projectIndex" : 2
				},
				{
					"directoryIndex" : 14,
					"id" : "select-support-test_int-vec.9.1.1::@c593a3635781ae508a1e",
					"jsonFile" : "target-select-support-test_int-vec.9.1.1-Debug-67eb5302a552f2260dea.json",
					"name" : "select-support-test_int-vec.9.1.1",
					"projectIndex" : 2
				},
				{
					"directoryIndex" : 14,
					"id" : "select_support_test::@c593a3635781ae508a1e",
					"jsonFile" : "target-select_support_test-Debug-6fc96ca428f5ab8ecb07.json",
					"name" : "select_support_test",
					"projectIndex" : 2
				},
				{
					"directoryIndex" : 14,
					"id" : "sorted-int-stack-test::@c593a3635781ae508a1e",
					"jsonFile" : "target-sorted-int-stack-test-Debug-11507ae379ef4f3f5605.json",
					"name" : "sorted-int-stack-test",
					"projectIndex" : 2
				},
				{
					"directoryIndex" : 14,
					"id" : "sorted-stack-support-test::@c593a3635781ae508a1e",
					"jsonFile" : "target-sorted-stack-support-test-Debug-750ed2d8adfa70740852.json",
					"name" : "sorted-stack-support-test",
					"projectIndex" : 2
				},
				{
					"directoryIndex" : 14,
					"id" : "sorted_int_stack_test::@c593a3635781ae508a1e",
					"jsonFile" : "target-sorted_int_stack_test-Debug-df1104bccf7f149614f4.json",
					"name" : "sorted_int_stack_test",
					"projectIndex" : 2
				},
				{
					"directoryIndex" : 14,
					"id" : "sorted_stack_support_test::@c593a3635781ae508a1e",
					"jsonFile" : "target-sorted_stack_support_test-Debug-76ecd229f1909cc1245a.json",
					"name" : "sorted_stack_support_test",
					"projectIndex" : 2
				},
				{
					"directoryIndex" : 14,
					"id" : "test-sdsl::@c593a3635781ae508a1e",
					"jsonFile" : "target-test-sdsl-Debug-a42b897ecead8738302b.json",
					"name" : "test-sdsl",
					"projectIndex" : 2
				},
				{
					"directoryIndex" : 15,
					"id" : "uninstall::@1fa18d2fea208eaa65c3",
					"jsonFile" : "target-uninstall-Debug-24378095198b5ecf7dcc.json",
					"name" : "uninstall",
					"projectIndex" : 5
				},
				{
					"directoryIndex" : 6,
					"id" : "uninstall::@6cb61072328088917163",
					"jsonFile" : "target-uninstall-Debug-d0eda8f769b59690ec93.json",
					"name" : "uninstall",
					"projectIndex" : 3
				},
				{
					"directoryIndex" : 4,
					"id" : "uninstall-sdsl::@4721196b8ed7a1e15cc7",
					"jsonFile" : "target-uninstall-sdsl-Debug-54b7a4e22bcf9769ba31.json",
					"name" : "uninstall-sdsl",
					"projectIndex" : 2
				},
				{
					"directoryIndex" : 14,
					"id" : "wt-byte-test::@c593a3635781ae508a1e",
					"jsonFile" : "target-wt-byte-test-Debug-b026fde39cc3d424605e.json",
					"name" : "wt-byte-test",
					"projectIndex" : 2
				},
				{
					"directoryIndex" : 14,
					"id" : "wt-byte-test_100a.txt::@c593a3635781ae508a1e",
					"jsonFile" : "target-wt-byte-test_100a.txt-Debug-ead71ff2baa86e5b1926.json",
					"name" : "wt-byte-test_100a.txt",
					"projectIndex" : 2
				},
				{
					"directoryIndex" : 14,
					"id" : "wt-byte-test_all_symbols.txt::@c593a3635781ae508a1e",
					"jsonFile" : "target-wt-byte-test_all_symbols.txt-Debug-19e83dbdd7f4e024c09a.json",
					"name" : "wt-byte-test_all_symbols.txt",
					"projectIndex" : 2
				},
				{
					"directoryIndex" : 14,
					"id" : "wt-byte-test_empty.txt::@c593a3635781ae508a1e",
					"jsonFile" : "target-wt-byte-test_empty.txt-Debug-9364c80a7e45c0f53b35.json",
					"name" : "wt-byte-test_empty.txt",
					"projectIndex" : 2
				},
				{
					"directoryIndex" : 14,
					"id" : "wt-byte-test_example01.txt::@c593a3635781ae508a1e",
					"jsonFile" : "target-wt-byte-test_example01.txt-Debug-462637bb50153f71aceb.json",
					"name" : "wt-byte-test_example01.txt",
					"projectIndex" : 2
				},
				{
					"directoryIndex" : 14,
					"id" : "wt-byte-test_faust.txt::@c593a3635781ae508a1e",
					"jsonFile" : "target-wt-byte-test_faust.txt-Debug-1c3863fc7491924c8633.json",
					"name" : "wt-byte-test_faust.txt",
					"projectIndex" : 2
				},
				{
					"directoryIndex" : 14,
					"id" : "wt-int-test::@c593a3635781ae508a1e",
					"jsonFile" : "target-wt-int-test-Debug-a3187c3e353d08b037d8.json",
					"name" : "wt-int-test",
					"projectIndex" : 2
				},
				{
					"directoryIndex" : 14,
					"id" : "wt-int-test_int-vec.0.1.0::@c593a3635781ae508a1e",
					"jsonFile" : "target-wt-int-test_int-vec.0.1.0-Debug-257237710aad69c32017.json",
					"name" : "wt-int-test_int-vec.0.1.0",
					"projectIndex" : 2
				},
				{
					"directoryIndex" : 14,
					"id" : "wt-int-test_int-vec.100000.18.r::@c593a3635781ae508a1e",
					"jsonFile" : "target-wt-int-test_int-vec.100000.18.r-Debug-2aa6077039769091a1a3.json",
					"name" : "wt-int-test_int-vec.100000.18.r",
					"projectIndex" : 2
				},
				{
					"directoryIndex" : 14,
					"id" : "wt-int-test_int-vec.100023.1.0::@c593a3635781ae508a1e",
					"jsonFile" : "target-wt-int-test_int-vec.100023.1.0-Debug-b06b627e2021ef0b376e.json",
					"name" : "wt-int-test_int-vec.100023.1.0",
					"projectIndex" : 2
				},
				{
					"directoryIndex" : 14,
					"id" : "wt-int-test_int-vec.1023.1.0::@c593a3635781ae508a1e",
					"jsonFile" : "target-wt-int-test_int-vec.1023.1.0-Debug-47eb0486d35f7a86f48d.json",
					"name" : "wt-int-test_int-vec.1023.1.0",
					"projectIndex" : 2
				},
				{
					"directoryIndex" : 14,
					"id" : "wt-int-test_int-vec.64.2.0::@c593a3635781ae508a1e",
					"jsonFile" : "target-wt-int-test_int-vec.64.2.0-Debug-ad1f4ec83ba64023afb2.json",
					"name" : "wt-int-test_int-vec.64.2.0",
					"projectIndex" : 2
				},
				{
					"directoryIndex" : 14,
					"id" : "wt_byte_test::@c593a3635781ae508a1e",
					"jsonFile" : "target-wt_byte_test-Debug-e407087b758305d01fb9.json",
					"name" : "wt_byte_test",
					"projectIndex" : 2
				},
				{
					"directoryIndex" : 14,
					"id" : "wt_int_test::@c593a3635781ae508a1e",
					"jsonFile" : "target-wt_int_test-Debug-103fb6327cc33cda04e3.json",
					"name" : "wt_int_test",
					"projectIndex" : 2
				},
				{
					"directoryIndex" : 14,
					"id" : "zarathustra.txt::@c593a3635781ae508a1e",
					"jsonFile" : "target-zarathustra.txt-Debug-82cd22d816fe09e76854.json",
					"name" : "zarathustra.txt",
					"projectIndex" : 2
				}
			]
		}
	],
	"kind" : "codemodel",
	"paths" : 
	{
		"build" : "/Users/yuhong/CLionProjects/rapid_check/cmake-build-debug",
		"source" : "/Users/yuhong/CLionProjects/rapid_check"
	},
	"version" : 
	{
		"major" : 2,
		"minor" : 5
	}
}
